pomeloabc_OI/__init__.py
pomeloabc_OI/Generator/Const.py
pomeloabc_OI/Generator/Graph.py
pomeloabc_OI/Generator/IO.py
pomeloabc_OI/Generator/Maths.py
pomeloabc_OI/Generator/String.py
pomeloabc_OI/Generator/Utils.py
pomeloabc_OI/Generator/__init__.py
pomeloabc_OI/OJHelper/__init__.py
pomeloabc_OI/OJHelper/Atcoder/__init__.py
pomeloabc_OI/OJHelper/Codeforces/__init__.py
pomeloabc_OI/OJHelper/Luogu/Const.py
pomeloabc_OI/OJHelper/Luogu/Contest.py
pomeloabc_OI/OJHelper/Luogu/Problem.py
pomeloabc_OI/OJHelper/Luogu/Record.py
pomeloabc_OI/OJHelper/Luogu/User.py
pomeloabc_OI/OJHelper/Luogu/Utils.py
pomeloabc_OI/OJHelper/Luogu/__init__.py
pomeloabc_OI/Utils/Clapper.py
pomeloabc_OI/Utils/Differ.py
pomeloabc_OI/Utils/Documenter.py
pomeloabc_OI/Utils/RSA.py
pomeloabc_OI/Utils/Similarizer.py
pomeloabc_OI/Utils/__init__.py
pomeloabc_OI-1.0.1.dist-info/LICENSE
pomeloabc_OI-1.0.1.dist-info/METADATA
pomeloabc_OI-1.0.1.dist-info/WHEEL
pomeloabc_OI-1.0.1.dist-info/top_level.txt
pomeloabc_OI-1.0.1.dist-info/RECORD
