Metadata-Version: 2.1
Name: pomeloabc_OI
Version: 1.0.1
Summary: This tool can help you more conveniently perform some operations.
Home-page: https://github.com/AndyPomeloMars/pomeloabc_OI
Author: AndyPomeloMars
Author-email: andypomelomars@163.com
Classifier: Programming Language :: Python :: 3
Classifier: License :: OSI Approved :: MIT License
Classifier: Operating System :: OS Independent
Requires-Python: >=3.8
License-File: LICENSE
